site_scout/__init__.py
site_scout/__main__.py
site_scout/args.py
site_scout/browser_wrapper.py
site_scout/explorer.py
site_scout/fenix_wrapper.py
site_scout/firefox_wrapper.py
site_scout/main.py
site_scout/reporter.py
site_scout/site_scout.py
site_scout/split_collection.py
site_scout/test_args.py
site_scout/test_explorer.py
site_scout/test_fenix_wrapper.py
site_scout/test_firefox_wrapper.py
site_scout/test_main.py
site_scout/test_reporter.py
site_scout/test_site_scout.py
site_scout/test_split_collection.py
site_scout/test_url.py
site_scout/test_url_collection.py
site_scout/test_url_db.py
site_scout/url.py
site_scout/url_collection.py
site_scout/url_db.py
site_scout/resources/prefpicker.yml
site_scout-5.4.1.dist-info/licenses/LICENSE.md
site_scout-5.4.1.dist-info/METADATA
site_scout-5.4.1.dist-info/WHEEL
site_scout-5.4.1.dist-info/entry_points.txt
site_scout-5.4.1.dist-info/top_level.txt
site_scout-5.4.1.dist-info/RECORD
