Metadata-Version: 2.4
Name: site-scout
Version: 5.4.1
Summary: A tool to identify and report browser issues triggered by visiting a list of URLs.
Home-page: https://github.com/MozillaSecurity/site-scout
Author: Tyson Smith
Author-email: twsmith@mozilla.com
Maintainer: Mozilla Fuzzing Team
Maintainer-email: fuzzing@mozilla.com
License: MPL 2.0
Keywords: automation testing
Classifier: Intended Audience :: Developers
Classifier: License :: OSI Approved :: Mozilla Public License 2.0 (MPL 2.0)
Classifier: Programming Language :: Python :: 3
Classifier: Topic :: Software Development :: Testing
Requires-Python: >=3.10
License-File: LICENSE.md
Requires-Dist: ffpuppet>=0.16.0
Requires-Dist: fxpoppet>=0.4.0
Requires-Dist: FuzzManager
Requires-Dist: page-explorer>=0.8.0
Requires-Dist: prefpicker>=1.1.0
Requires-Dist: PyYAML
Requires-Dist: tldextract>=5.1.2
Provides-Extra: dev
Requires-Dist: pre-commit; extra == "dev"
Requires-Dist: tox; extra == "dev"
Dynamic: license-file
